OpenOCTAAnalyzer/OpenOCTAAnalyzer.py
OpenOCTAAnalyzer/OpenOCTAAnalyzerFilters.py
OpenOCTAAnalyzer/__init__.py
OpenOCTAAnalyzer-1.0.0.dist-info/LICENSE
OpenOCTAAnalyzer-1.0.0.dist-info/METADATA
OpenOCTAAnalyzer-1.0.0.dist-info/WHEEL
OpenOCTAAnalyzer-1.0.0.dist-info/top_level.txt
OpenOCTAAnalyzer-1.0.0.dist-info/RECORD
