Metadata-Version: 2.1
Name: OpenOCTAAnalyzer
Version: 1.0.0
Summary: An open source OCTA Analyzer
Author-email: Claus von der Burchard <claus.vonderburchard@uksh.de>
Project-URL: Homepage, https://github.com/pypa/sampleproject
Project-URL: Issues, https://github.com/pypa/sampleproject/issues
Classifier: Programming Language :: Python :: 3
Classifier: License :: OSI Approved :: MIT License
Classifier: Operating System :: OS Independent
Requires-Python: >=3.8
License-File: LICENSE
